autoattn/__init__.py
autoattn/auto.py
autoattn/backends/__init__.py
autoattn/backends/base.py
autoattn/backends/dense.py
autoattn/backends/flash.py
autoattn/backends/local.py
autoattn-0.1.0.dist-info/licenses/LICENSE
autoattn-0.1.0.dist-info/METADATA
autoattn-0.1.0.dist-info/WHEEL
autoattn-0.1.0.dist-info/top_level.txt
autoattn-0.1.0.dist-info/RECORD
