Metadata-Version: 2.4
Name: autoattn
Version: 0.1.0
Summary: Automatic routing between attention backends (dense, flash, sparse)
Author: Achintya Paningapalli
License: MIT
Project-URL: Homepage, https://github.com/achintya-p/auto_attn
Project-URL: Repository, https://github.com/achintya-p/auto_attn
Keywords: attention,transformer,llm,flash-attention,pytorch
Classifier: Development Status :: 3 - Alpha
Classifier: Intended Audience :: Developers
Classifier: Intended Audience :: Science/Research
Classifier: License :: OSI Approved :: MIT License
Classifier: Programming Language :: Python :: 3
Classifier: Programming Language :: Python :: 3.9
Classifier: Programming Language :: Python :: 3.10
Classifier: Programming Language :: Python :: 3.11
Classifier: Topic :: Scientific/Engineering :: Artificial Intelligence
Requires-Python: >=3.9
License-File: LICENSE
Requires-Dist: torch>=2.0
Provides-Extra: dev
Requires-Dist: pytest; extra == "dev"
Requires-Dist: pytest-cov; extra == "dev"
Dynamic: license-file
